fastmiddleware/__init__.py
fastmiddleware/ab_testing.py
fastmiddleware/accept_language.py
fastmiddleware/api_version_header.py
fastmiddleware/audit.py
fastmiddleware/authentication.py
fastmiddleware/bandwidth.py
fastmiddleware/base.py
fastmiddleware/basic_auth.py
fastmiddleware/bearer_auth.py
fastmiddleware/bot_detection.py
fastmiddleware/bulkhead.py
fastmiddleware/cache.py
fastmiddleware/chaos.py
fastmiddleware/circuit_breaker.py
fastmiddleware/client_hints.py
fastmiddleware/compression.py
fastmiddleware/conditional_request.py
fastmiddleware/content_negotiation.py
fastmiddleware/content_type.py
fastmiddleware/context.py
fastmiddleware/correlation.py
fastmiddleware/cors.py
fastmiddleware/cost_tracking.py
fastmiddleware/csp_report.py
fastmiddleware/csrf.py
fastmiddleware/data_masking.py
fastmiddleware/deprecation.py
fastmiddleware/early_hints.py
fastmiddleware/error_handler.py
fastmiddleware/etag.py
fastmiddleware/exception_handler.py
fastmiddleware/factory.py
fastmiddleware/feature_flag.py
fastmiddleware/geoip.py
fastmiddleware/graceful_shutdown.py
fastmiddleware/hateoas.py
fastmiddleware/header_transform.py
fastmiddleware/health.py
fastmiddleware/honeypot.py
fastmiddleware/https_redirect.py
fastmiddleware/idempotency.py
fastmiddleware/ip_filter.py
fastmiddleware/json_schema.py
fastmiddleware/load_shedding.py
fastmiddleware/locale.py
fastmiddleware/logging.py
fastmiddleware/maintenance.py
fastmiddleware/method_override.py
fastmiddleware/metrics.py
fastmiddleware/no_cache.py
fastmiddleware/origin.py
fastmiddleware/path_rewrite.py
fastmiddleware/payload_size.py
fastmiddleware/permissions_policy.py
fastmiddleware/profiling.py
fastmiddleware/proxy.py
fastmiddleware/py.typed
fastmiddleware/quota.py
fastmiddleware/rate_limit.py
fastmiddleware/real_ip.py
fastmiddleware/redirect.py
fastmiddleware/referrer_policy.py
fastmiddleware/replay_prevention.py
fastmiddleware/request_coalescing.py
fastmiddleware/request_context.py
fastmiddleware/request_dedup.py
fastmvc_middleware-0.6.4.dist-info/METADATA
fastmvc_middleware-0.6.4.dist-info/WHEEL
fastmvc_middleware-0.6.4.dist-info/licenses/LICENSE
fastmvc_middleware-0.6.4.dist-info/RECORD
