Metadata-Version: 2.4
Name: fastmvc-middleware
Version: 0.6.4
Summary: Production-ready middleware collection with 90+ components for FastAPI/Starlette applications
Project-URL: Homepage, https://github.com/shregar1/fastmvc-middleware
Project-URL: Documentation, https://github.com/shregar1/fastmvc-middleware#readme
Project-URL: Repository, https://github.com/shregar1/fastmvc-middleware
Project-URL: Issues, https://github.com/shregar1/fastmvc-middleware/issues
Project-URL: Changelog, https://github.com/shregar1/fastmvc-middleware/blob/main/CHANGELOG.md
Author-email: Shivansh Sengar <sengarsinghshivansh@gmail.com>, Shreyansh Sengar <sengarsinghshreyansh@gmail.com>
Maintainer-email: Shivansh Sengar <sengarsinghshivansh@gmail.com>, Shreyansh Sengar <sengarsinghshreyansh@gmail.com>
License-Expression: MIT
License-File: LICENSE
Keywords: ab-testing,api,audit-logging,authentication,bot-detection,bulkhead,caching,circuit-breaker,compression,cors,csrf,fastapi,feature-flags,geoip,health-check,idempotency,jwt,logging,metrics,middleware,multi-tenant,prometheus,rate-limiting,security,session,starlette
Classifier: Development Status :: 4 - Beta
Classifier: Environment :: Web Environment
Classifier: Framework :: FastAPI
Classifier: Intended Audience :: Developers
Classifier: License :: OSI Approved :: MIT License
Classifier: Operating System :: OS Independent
Classifier: Programming Language :: Python :: 3
Classifier: Programming Language :: Python :: 3.10
Classifier: Programming Language :: Python :: 3.11
Classifier: Programming Language :: Python :: 3.12
Classifier: Programming Language :: Python :: 3.13
Classifier: Programming Language :: Python :: 3.14
Classifier: Topic :: Internet :: WWW/HTTP :: HTTP Servers
Classifier: Topic :: Internet :: WWW/HTTP :: WSGI :: Middleware
Classifier: Topic :: Security
Classifier: Topic :: Software Development :: Libraries :: Python Modules
Classifier: Topic :: System :: Monitoring
Classifier: Typing :: Typed
Requires-Python: >=3.10
Requires-Dist: starlette>=0.27.0
Provides-Extra: all
Requires-Dist: httpx>=0.24.0; extra == 'all'
Requires-Dist: pyjwt>=2.0.0; extra == 'all'
Provides-Extra: dev
Requires-Dist: bandit[toml]>=1.7.0; extra == 'dev'
Requires-Dist: build>=1.0.0; extra == 'dev'
Requires-Dist: fastapi>=0.100.0; extra == 'dev'
Requires-Dist: httpx>=0.24.0; extra == 'dev'
Requires-Dist: mypy>=1.0.0; extra == 'dev'
Requires-Dist: pre-commit>=3.0.0; extra == 'dev'
Requires-Dist: pyjwt>=2.0.0; extra == 'dev'
Requires-Dist: pytest-asyncio>=0.21.0; extra == 'dev'
Requires-Dist: pytest-cov>=4.0.0; extra == 'dev'
Requires-Dist: pytest-xdist>=3.0.0; extra == 'dev'
Requires-Dist: pytest>=7.0.0; extra == 'dev'
Requires-Dist: ruff>=0.1.0; extra == 'dev'
Requires-Dist: twine>=4.0.0; extra == 'dev'
Requires-Dist: uvicorn>=0.20.0; extra == 'dev'
Provides-Extra: jwt
Requires-Dist: pyjwt>=2.0.0; extra == 'jwt'
Provides-Extra: proxy
Requires-Dist: httpx>=0.24.0; extra == 'proxy'
